loggan/__init__.py
loggan/loggan.py
loggan-0.1.2.dist-info/licenses/LICENSE
loggan-0.1.2.dist-info/METADATA
loggan-0.1.2.dist-info/WHEEL
loggan-0.1.2.dist-info/top_level.txt
loggan-0.1.2.dist-info/RECORD
