Metadata-Version: 2.4
Name: loggan
Version: 0.1.2
Summary: Custom loggers for Python
Author-email: "(gcca)" <git@gcca.dev>
License-Expression: GPL-3.0-or-later
Project-URL: Homepage, https://github.com/gcca/loggan
Project-URL: Repository, https://github.com/gcca/loggan.git
Project-URL: Issues, https://github.com/gcca/loggan/issues
Classifier: Programming Language :: Python :: 3
Classifier: Programming Language :: Python :: 3.13
Classifier: Operating System :: OS Independent
Requires-Python: >=3.8
License-File: LICENSE
Dynamic: license-file
